telegramtui/__init__.py
telegramtui/__main__.py
telegramtui/src/ContactsForm.py
telegramtui/src/ForwardMessageForm.py
telegramtui/src/MainForm.py
telegramtui/src/MessageInfoForm.py
telegramtui/src/RemoveMessageForm.py
telegramtui/src/SendFileForm.py
telegramtui/src/__init__.py
telegramtui/src/aalib.py
telegramtui/src/chatBox.py
telegramtui/src/config.py
telegramtui/src/functionalBox.py
telegramtui/src/inputBox.py
telegramtui/src/messageBox.py
telegramtui/src/telegramApi.py
telegramtui/src/ui.py
telegramtui/src/npyscreen/__init__.py
telegramtui/src/npyscreen/apNPSApplication.py
telegramtui/src/npyscreen/apNPSApplicationAdvanced.py
telegramtui/src/npyscreen/apNPSApplicationEvents.py
telegramtui/src/npyscreen/apNPSApplicationManaged.py
telegramtui/src/npyscreen/apOptions.py
telegramtui/src/npyscreen/eveventhandler.py
telegramtui/src/npyscreen/fmActionForm.py
telegramtui/src/npyscreen/fmActionFormV2.py
telegramtui/src/npyscreen/fmFileSelector.py
telegramtui/src/npyscreen/fmForm.py
telegramtui/src/npyscreen/fmFormMultiPage.py
telegramtui/src/npyscreen/fmFormMutt.py
telegramtui/src/npyscreen/fmFormMuttActive.py
telegramtui/src/npyscreen/fmFormWithMenus.py
telegramtui/src/npyscreen/fmPopup.py
telegramtui/src/npyscreen/fm_form_edit_loop.py
telegramtui/src/npyscreen/globals.py
telegramtui/src/npyscreen/muMenu.py
telegramtui/src/npyscreen/muNewMenu.py
telegramtui/src/npyscreen/npysGlobalOptions.py
telegramtui/src/npyscreen/npysNPSFilteredData.py
telegramtui/src/npyscreen/npysThemeManagers.py
telegramtui/src/npyscreen/npysThemes.py
telegramtui/src/npyscreen/npysTree.py
telegramtui/src/npyscreen/npyspmfuncs.py
telegramtui/src/npyscreen/npyssafewrapper.py
telegramtui/src/npyscreen/proto_fm_screen_area.py
telegramtui/src/npyscreen/stdfmemail.py
telegramtui/src/npyscreen/utilNotify.py
telegramtui/src/npyscreen/util_viewhelp.py
telegramtui/src/npyscreen/wgFormControlCheckbox.py
telegramtui/src/npyscreen/wgNMenuDisplay.py
telegramtui/src/npyscreen/wgannotatetextbox.py
telegramtui-0.1.2.dist-info/LICENSE
telegramtui-0.1.2.dist-info/METADATA
telegramtui-0.1.2.dist-info/WHEEL
telegramtui-0.1.2.dist-info/entry_points.txt
telegramtui-0.1.2.dist-info/top_level.txt
telegramtui-0.1.2.dist-info/RECORD
