Metadata-Version: 2.1
Name: telegramtui
Version: 0.1.2
Summary: Telegram client on your console
Home-page: https://github.com/vtr0n/TelegramTUI
Author: Valery Krasnoselsky
Author-email: valery.krasnoselsky@gmail.com
License: MIT
Keywords: telegram telegramtui telegramcli telegram-cli telegram-tui tui
Platform: UNKNOWN
Classifier: Programming Language :: Python :: 3
Classifier: Programming Language :: Python :: 3.4
Classifier: Programming Language :: Python :: 3.5
Classifier: Programming Language :: Python :: 3.6
Classifier: Programming Language :: Python :: 3.7
Classifier: License :: OSI Approved :: MIT License
Requires-Python: >=3.4
Requires-Dist: Pillow (==6.2.1)
Requires-Dist: pyaes (==1.6.1)
Requires-Dist: pyasn1 (==0.4.7)
Requires-Dist: PySocks (==1.7.1)
Requires-Dist: python-aalib (==0.3.2)
Requires-Dist: rsa (==4.0)
Requires-Dist: Telethon (==0.19.1.6)
Requires-Dist: windows-curses (>=2.0) ; platform_system == "Windows"
